utils/__init__.py
utils/get_data.py
utils/img_pdf.py
utils/nsfc_download.py
nsfc_download-0.0.1.dist-info/METADATA
nsfc_download-0.0.1.dist-info/WHEEL
nsfc_download-0.0.1.dist-info/entry_points.txt
nsfc_download-0.0.1.dist-info/top_level.txt
nsfc_download-0.0.1.dist-info/RECORD
